mesa_frames/__init__.py
mesa_frames/types_.py
mesa_frames/utils.py
mesa_frames/abstract/__init__.py
mesa_frames/abstract/agents.py
mesa_frames/abstract/mixin.py
mesa_frames/abstract/space.py
mesa_frames/concrete/__init__.py
mesa_frames/concrete/agents.py
mesa_frames/concrete/model.py
mesa_frames/concrete/pandas/__init__.py
mesa_frames/concrete/pandas/agentset.py
mesa_frames/concrete/pandas/mixin.py
mesa_frames/concrete/pandas/space.py
mesa_frames/concrete/polars/__init__.py
mesa_frames/concrete/polars/agentset.py
mesa_frames/concrete/polars/mixin.py
mesa_frames/concrete/polars/space.py
mesa_frames-0.1.0a0.dist-info/METADATA
mesa_frames-0.1.0a0.dist-info/WHEEL
mesa_frames-0.1.0a0.dist-info/licenses/LICENSE
mesa_frames-0.1.0a0.dist-info/RECORD
