Metadata-Version: 2.3
Name: mesa_frames
Version: 0.1.0a0
Summary: An extension to the Mesa framework which uses pandas/Polars DataFrames for enhanced performance
Project-URL: Documentation, https://adamamer20.github.io/mesa-frames
Project-URL: Repository, https://github.com/adamamer20/mesa-frames.git
Author: Adam Amer
License: MIT
License-File: LICENSE
Keywords: agent-based-modeling,agent-based-modelling,complex-systems,complexity-analysis,gis,mesa,modeling-agents,pandas,simulation,simulation-environment,simulation-framework,spatial-models
Classifier: Development Status :: 3 - Alpha
Classifier: Intended Audience :: Science/Research
Classifier: License :: OSI Approved :: MIT License
Classifier: Programming Language :: Python :: 3
Classifier: Topic :: Scientific/Engineering :: Artificial Life
Requires-Python: >=3.8
Requires-Dist: numpy~=1.26
Requires-Dist: pandas>=2.2
Requires-Dist: polars>=1.0.0
Requires-Dist: pyarrow
Requires-Dist: typing-extensions>=4.9
Provides-Extra: dev
Requires-Dist: autodocsumm; extra == 'dev'
Requires-Dist: mesa; extra == 'dev'
Requires-Dist: mkdocs-git-revision-date-localized-plugin; extra == 'dev'
Requires-Dist: mkdocs-jupyter; extra == 'dev'
Requires-Dist: mkdocs-material; extra == 'dev'
Requires-Dist: mkdocs-minify-plugin; extra == 'dev'
Requires-Dist: numpydoc; extra == 'dev'
Requires-Dist: perfplot; extra == 'dev'
Requires-Dist: pydata-sphinx-theme; extra == 'dev'
Requires-Dist: pytest; extra == 'dev'
Requires-Dist: pytest-cov; extra == 'dev'
Requires-Dist: seaborn; extra == 'dev'
Requires-Dist: sphinx; extra == 'dev'
Requires-Dist: sphinx-copybutton; extra == 'dev'
Requires-Dist: sphinx-design; extra == 'dev'
Requires-Dist: sphinx-rtd-theme; extra == 'dev'
Requires-Dist: typeguard; extra == 'dev'
Provides-Extra: docs
Requires-Dist: autodocsumm; extra == 'docs'
Requires-Dist: mkdocs-git-revision-date-localized-plugin; extra == 'docs'
Requires-Dist: mkdocs-jupyter; extra == 'docs'
Requires-Dist: mkdocs-material; extra == 'docs'
Requires-Dist: mkdocs-minify-plugin; extra == 'docs'
Requires-Dist: numpydoc; extra == 'docs'
Requires-Dist: perfplot; extra == 'docs'
Requires-Dist: pydata-sphinx-theme; extra == 'docs'
Requires-Dist: seaborn; extra == 'docs'
Requires-Dist: sphinx; extra == 'docs'
Requires-Dist: sphinx-copybutton; extra == 'docs'
Requires-Dist: sphinx-design; extra == 'docs'
Requires-Dist: sphinx-rtd-theme; extra == 'docs'
Provides-Extra: mkdocs
Requires-Dist: mkdocs-git-revision-date-localized-plugin; extra == 'mkdocs'
Requires-Dist: mkdocs-jupyter; extra == 'mkdocs'
Requires-Dist: mkdocs-material; extra == 'mkdocs'
Requires-Dist: mkdocs-minify-plugin; extra == 'mkdocs'
Provides-Extra: sphinx
Requires-Dist: autodocsumm; extra == 'sphinx'
Requires-Dist: numpydoc; extra == 'sphinx'
Requires-Dist: pydata-sphinx-theme; extra == 'sphinx'
Requires-Dist: sphinx; extra == 'sphinx'
Requires-Dist: sphinx-copybutton; extra == 'sphinx'
Requires-Dist: sphinx-design; extra == 'sphinx'
Requires-Dist: sphinx-rtd-theme; extra == 'sphinx'
Provides-Extra: test
Requires-Dist: pytest; extra == 'test'
Requires-Dist: pytest-cov; extra == 'test'
Requires-Dist: typeguard; extra == 'test'
